{"cameraMode":{"drawMode":0,"name":"Shaded","section":"Shading Mode"},"sceneLighting":true,"audioPlay":false,"sceneViewState":{"m_AlwaysRefresh":false,"showFog":true,"showSkybox":true,"showFlares":true,"showImageEffects":true,"showParticleSystems":true,"showVisualEffectGraphs":true,"m_FxEnabled":true},"in2DMode":false,"pivot":{"x":-1.2251124382019044,"y":0.4644451141357422,"z":-3.151451349258423},"rotation":{"x":-0.14041900634765626,"y":-0.07655574381351471,"z":0.010893727652728558,"w":-0.9870768189430237},"size":6.1700758934021,"orthographic":false}